LICENSE
README.rst
setup.py
depot/__init__.py
depot/_compat.py
depot/manager.py
depot/middleware.py
depot/utils.py
depot/validators.py
depot/fields/__init__.py
depot/fields/interfaces.py
depot/fields/ming.py
depot/fields/sqlalchemy.py
depot/fields/upload.py
depot/fields/filters/__init__.py
depot/fields/filters/thumbnails.py
depot/fields/specialized/__init__.py
depot/fields/specialized/image.py
depot/io/__init__.py
depot/io/awss3.py
depot/io/boto3.py
depot/io/gcs.py
depot/io/gridfs.py
depot/io/interfaces.py
depot/io/local.py
depot/io/memory.py
depot/io/utils.py
filedepot.egg-info/PKG-INFO
filedepot.egg-info/SOURCES.txt
filedepot.egg-info/dependency_links.txt
filedepot.egg-info/not-zip-safe
filedepot.egg-info/requires.txt
filedepot.egg-info/top_level.txt
tests/test_awss3_storage.py
tests/test_boto3_storage.py
tests/test_depot_manager.py
tests/test_fields_basic.py
tests/test_fields_ming.py
tests/test_fields_sqlalchemy.py
tests/test_gcs_storage.py
tests/test_gridfs_storage.py
tests/test_local_storage.py
tests/test_storage_interface.py
tests/test_wsgi_middleware.py