Metadata-Version: 2.1
Name: filedepot
Version: 0.11.0
Summary: Toolkit for storing files and attachments in web applications
Home-page: https://github.com/amol-/depot
Author: Alessandro Molina
Author-email: amol@turbogears.org
License: MIT
Keywords: storage files s3 gridfs mongodb aws sqlalchemy wsgi
Classifier: Environment :: Web Environment
Classifier: Topic :: Software Development :: Libraries :: Python Modules
Classifier: Programming Language :: Python :: 3
Classifier: Programming Language :: Python :: 2
Provides-Extra: testing
License-File: LICENSE
